unilogging/__init__.py
unilogging/context.py
unilogging/logger.py
unilogging/integrations/__init__.py
unilogging/integrations/dishka.py
unilogging-0.2.2.dist-info/METADATA
unilogging-0.2.2.dist-info/WHEEL
unilogging-0.2.2.dist-info/licenses/LICENSE
unilogging-0.2.2.dist-info/RECORD
