Metadata-Version: 2.4
Name: unilogging
Version: 0.2.2
Summary: A simple library for working with the context of logs.
Project-URL: Homepage, https://github.com/goduni/unilogging
Project-URL: Repository, https://github.com/goduni/unilogging
Project-URL: Issues, https://github.com/goduni/unilogging/issues
Author-email: Universe Interface <uni@goduni.me>
License: MIT
License-File: LICENSE
Keywords: context,logging,python-logging,structured-logging
Classifier: Intended Audience :: Developers
Classifier: License :: OSI Approved :: MIT License
Classifier: Operating System :: OS Independent
Classifier: Programming Language :: Python :: 3
Classifier: Programming Language :: Python :: 3.12
Classifier: Programming Language :: Python :: 3.13
Classifier: Programming Language :: Python :: 3.14
Requires-Python: >=3.12
Provides-Extra: dishka
Requires-Dist: dishka>=1.6.0; extra == 'dishka'
